leafpydome/__init__.py
leafpydome/auth.py
leafpydome/leaf.py
leafpydome-0.2.3.dist-info/METADATA
leafpydome-0.2.3.dist-info/RECORD
leafpydome-0.2.3.dist-info/WHEEL
leafpydome-0.2.3.dist-info/top_level.txt
