Metadata-Version: 2.1
Name: leafpydome
Version: 0.2.3
Summary: Lightweight python interface to the nissan leaf based on leafpy package.
Home-page: UNKNOWN
Author: UNKNOWN
Author-email: UNKNOWN
License: MIT
Platform: UNKNOWN
Requires-Dist: requests
Requires-Dist: pycryptodome
